{
  "main": {
    "id": "b34374f09518b05f",
    "type": "split",
    "children": [
      {
        "id": "b9d54dbea93c090f",
        "type": "tabs",
        "children": [
          {
            "id": "c65b5c7239bb0fcf",
            "type": "leaf",
            "state": {
              "type": "markdown",
              "state": {
                "file": "Vie Perso/Dnd/La naissance du mal/Sessions/Session 1 préparation.md",
                "mode": "source",
                "source": false
              },
              "icon": "lucide-file",
              "title": "Session 1 préparation"
            }
          },
          {
            "id": "b67280df2cf0486f",
            "type": "leaf",
            "state": {
              "type": "markdown",
              "state": {
                "file": "Vie Perso/Dnd/La naissance du mal/PNJ/Sylphia.md",
                "mode": "source",
                "source": false
              },
              "icon": "lucide-file",
              "title": "Sylphia"
            }
          }
        ],
        "currentTab": 1
      }
    ],
    "direction": "vertical"
  },
  "left": {
    "id": "4024ecf3d86e32b2",
    "type": "split",
    "children": [
      {
        "id": "f2c26174bc64bccd",
        "type": "tabs",
        "children": [
          {
            "id": "f43bdfbca956f596",
            "type": "leaf",
            "state": {
              "type": "file-explorer",
              "state": {
                "sortOrder": "alphabetical",
                "autoReveal": false
              },
              "icon": "lucide-folder-closed",
              "title": "Files"
            }
          },
          {
            "id": "9a4faad935100ea5",
            "type": "leaf",
            "state": {
              "type": "search",
              "state": {
                "query": "",
                "matchingCase": false,
                "explainSearch": false,
                "collapseAll": false,
                "extraContext": false,
                "sortOrder": "alphabetical"
              },
              "icon": "lucide-search",
              "title": "Search"
            }
          },
          {
            "id": "54a84df2ceb0c184",
            "type": "leaf",
            "state": {
              "type": "bookmarks",
              "state": {},
              "icon": "lucide-bookmark",
              "title": "Bookmarks"
            }
          }
        ]
      }
    ],
    "direction": "horizontal",
    "width": 300
  },
  "right": {
    "id": "9251dcfc2e25b1d8",
    "type": "split",
    "children": [
      {
        "id": "fe4bd5bc275e78d9",
        "type": "tabs",
        "children": [
          {
            "id": "9f0df47b22c6f875",
            "type": "leaf",
            "state": {
              "type": "backlink",
              "state": {
                "file": "Vie Perso/Dnd/La naissance du mal/PNJ/Sylphia.md",
                "collapseAll": false,
                "extraContext": false,
                "sortOrder": "alphabetical",
                "showSearch": false,
                "searchQuery": "",
                "backlinkCollapsed": false,
                "unlinkedCollapsed": true
              },
              "icon": "links-coming-in",
              "title": "Backlinks for Sylphia"
            }
          },
          {
            "id": "691ae1a5dcd7a2d0",
            "type": "leaf",
            "state": {
              "type": "outgoing-link",
              "state": {
                "file": "Vie Perso/Dnd/La naissance du mal/PNJ/Sylphia.md",
                "linksCollapsed": false,
                "unlinkedCollapsed": true
              },
              "icon": "links-going-out",
              "title": "Outgoing links from Sylphia"
            }
          },
          {
            "id": "20e7cf63137ea331",
            "type": "leaf",
            "state": {
              "type": "tag",
              "state": {
                "sortOrder": "frequency",
                "useHierarchy": true,
                "showSearch": false,
                "searchQuery": ""
              },
              "icon": "lucide-tags",
              "title": "Tags"
            }
          },
          {
            "id": "41e4b4ef8043e35c",
            "type": "leaf",
            "state": {
              "type": "outline",
              "state": {
                "file": "Vie Perso/Dnd/La naissance du mal/PNJ/Sylphia.md",
                "followCursor": false,
                "showSearch": false,
                "searchQuery": ""
              },
              "icon": "lucide-list",
              "title": "Outline of Sylphia"
            }
          },
          {
            "id": "9feee8e18e9a6683",
            "type": "leaf",
            "state": {
              "type": "git-view",
              "state": {},
              "icon": "git-pull-request",
              "title": "Source Control"
            }
          },
          {
            "id": "d645c40c12afaf9d",
            "type": "leaf",
            "state": {
              "type": "initiative-tracker-view",
              "state": {},
              "icon": "initiative-tracker",
              "title": "Initiative Tracker"
            }
          }
        ],
        "currentTab": 4
      },
      {
        "id": "26a1f00c7f821524",
        "type": "tabs",
        "children": [
          {
            "id": "6d6977f270979616",
            "type": "leaf",
            "state": {
              "type": "initiative-tracker-creature-view",
              "state": {},
              "icon": "initiative-tracker-creature-view",
              "title": "Combatant"
            }
          }
        ]
      }
    ],
    "direction": "horizontal",
    "width": 408.5
  },
  "left-ribbon": {
    "hiddenItems": {
      "obsidian-leaflet-plugin:Open Leaflet Map": false,
      "templater-obsidian:Templater": false,
      "bases:Create new base": false,
      "switcher:Open quick switcher": false,
      "graph:Open graph view": false,
      "canvas:Create new canvas": false,
      "daily-notes:Open today's daily note": false,
      "templates:Insert template": false,
      "command-palette:Open command palette": false,
      "obsidian-git:Open Git source control": false,
      "initiative-tracker:Initiative Tracker Encounter Builder": false,
      "obsidian-5e-statblocks:Open Creature pane": false
    }
  },
  "active": "b67280df2cf0486f",
  "lastOpenFiles": [
    "Vie Perso/Dnd/La naissance du mal/Sessions/Session 1 préparation.md",
    "Vie Perso/Dnd/La naissance du mal/PNJ/Sylphia.md",
    "Vie Perso/Dnd/La naissance du mal/PNJ/__PNJ.md",
    "Vie Perso/Dnd/La naissance du mal/PNJ/Marcus.md",
    "Vie Perso/Dnd/La naissance du mal/Sessions/Session 1.md",
    "Vie Perso/Dnd/La naissance du mal/Places/Chapelle en ruine.md",
    "Vie Perso/Dnd/La naissance du mal/Places/__Places.md",
    "Vie Perso/Dnd/La naissance du mal/Sessions/__Sessions.md",
    "Vie Perso/Dnd/La naissance du mal/Places/Grisemarre.md",
    "Assets",
    "Vie Perso/Dnd/La naissance du mal/PNJ/Sieb.md",
    "Templates/Session.md",
    "Vie Perso/Dnd/La naissance du mal/Sessions/Untitled.md",
    "Templates/Session Preparation.md",
    "Vie Perso/Dnd/La naissance du mal/Players/Seraphine.md",
    "Vie Perso/Dnd/La naissance du mal/Players/Kara.md",
    "Vie Perso/Dnd/La naissance du mal/Players/Holg.md",
    "temp.md",
    "Untitled.canvas",
    "Vie Perso/Dnd/La naissance du mal/History/Les écorchés.md",
    "Templates.md",
    "Vie Perso/Lecture/Livre/Return of the lazy dungeon master.md",
    "Vie Perso/Dnd/La naissance du mal/Items",
    "Vie Perso/Dnd/La naissance du mal/Sessions/Session 1 Preparation.md",
    "Templates",
    "Vie Perso/Dnd/La naissance du mal/Sessions",
    "Vie Perso/Dnd/La naissance du mal/Players/Old/Nual Sumal.md",
    "Vie Perso/Lecture/Livre",
    "Vie Perso/Visionnage/Série/Time bandit.md",
    "Vie Perso/Visionnage/Série/Slow horses.md",
    "Vie Perso/Visionnage/Série/Miracle workers.md",
    "Vie Perso/Visionnage/Série",
    "Vie Perso/Visionnage/Anime",
    "Vie Perso/Visionnage",
    "Vie Perso/Lecture/Manga",
    "Vie Perso/Lecture"
  ]
}